{"metadata": {"dbt_schema_version": "https://schemas.getdbt.com/dbt/run-results/v4.json", "dbt_version": "1.0.0", "generated_at": "2022-03-29T18:46:12.382095Z", "invocation_id": "112d7bcb-fbaf-4f4a-ab56-b4ffe2aac542", "env": {}}, "results": [{"status": "success", "timing": [{"name": "compile", "started_at": "2022-03-29T18:46:09.594702Z", "completed_at": "2022-03-29T18:46:09.611626Z"}, {"name": "execute", "started_at": "2022-03-29T18:46:09.611923Z", "completed_at": "2022-03-29T18:46:09.611938Z"}], "thread_id": "Thread-1", "execution_time": 0.017896175384521484, "adapter_response": {}, "message": null, "failures": null, "unique_id": "model.smartpill.quickbook_accounts"}, {"status": "success", "timing": [{"name": "compile", "started_at": "2022-03-29T18:46:09.613567Z", "completed_at": "2022-03-29T18:46:09.626277Z"}, {"name": "execute", "started_at": "2022-03-29T18:46:09.626550Z", "completed_at": "2022-03-29T18:46:09.626562Z"}], "thread_id": "Thread-1", "execution_time": 0.013721227645874023, "adapter_response": {}, "message": null, "failures": null, "unique_id": "model.smartpill.quickbook_bill_payments"}, {"status": "success", "timing": [{"name": "compile", "started_at": "2022-03-29T18:46:09.628164Z", "completed_at": "2022-03-29T18:46:09.642728Z"}, {"name": "execute", "started_at": "2022-03-29T18:46:09.642996Z", "completed_at": "2022-03-29T18:46:09.643008Z"}], "thread_id": "Thread-1", "execution_time": 0.015573501586914062, "adapter_response": {}, "message": null, "failures": null, "unique_id": "model.smartpill.quickbook_bills"}, {"status": "success", "timing": [{"name": "compile", "started_at": "2022-03-29T18:46:09.644596Z", "completed_at": "2022-03-29T18:46:09.654911Z"}, {"name": "execute", "started_at": "2022-03-29T18:46:09.655182Z", "completed_at": "2022-03-29T18:46:09.655193Z"}], "thread_id": "Thread-1", "execution_time": 0.011407852172851562, "adapter_response": {}, "message": null, "failures": null, "unique_id": "model.smartpill.quickbook_classes"}, {"status": "success", "timing": [{"name": "compile", "started_at": "2022-03-29T18:46:09.656768Z", "completed_at": "2022-03-29T18:46:09.672330Z"}, {"name": "execute", "started_at": "2022-03-29T18:46:09.672670Z", "completed_at": "2022-03-29T18:46:09.672684Z"}], "thread_id": "Thread-1", "execution_time": 0.01669001579284668, "adapter_response": {}, "message": null, "failures": null, "unique_id": "model.smartpill.quickbook_customers"}, {"status": "success", "timing": [{"name": "compile", "started_at": "2022-03-29T18:46:09.674210Z", "completed_at": "2022-03-29T18:46:09.685223Z"}, {"name": "execute", "started_at": "2022-03-29T18:46:09.685501Z", "completed_at": "2022-03-29T18:46:09.685514Z"}], "thread_id": "Thread-1", "execution_time": 0.012027502059936523, "adapter_response": {}, "message": null, "failures": null, "unique_id": "model.smartpill.quickbook_deposits"}, {"status": "success", "timing": [{"name": "compile", "started_at": "2022-03-29T18:46:09.687135Z", "completed_at": "2022-03-29T18:46:09.702092Z"}, {"name": "execute", "started_at": "2022-03-29T18:46:09.702370Z", "completed_at": "2022-03-29T18:46:09.702382Z"}], "thread_id": "Thread-1", "execution_time": 0.016042709350585938, "adapter_response": {}, "message": null, "failures": null, "unique_id": "model.smartpill.quickbook_invoices"}, {"status": "success", "timing": [{"name": "compile", "started_at": "2022-03-29T18:46:09.703767Z", "completed_at": "2022-03-29T18:46:09.721877Z"}, {"name": "execute", "started_at": "2022-03-29T18:46:09.722155Z", "completed_at": "2022-03-29T18:46:09.722167Z"}], "thread_id": "Thread-1", "execution_time": 0.019121885299682617, "adapter_response": {}, "message": null, "failures": null, "unique_id": "model.smartpill.quickbook_items"}, {"status": "success", "timing": [{"name": "compile", "started_at": "2022-03-29T18:46:09.723456Z", "completed_at": "2022-03-29T18:46:09.734509Z"}, {"name": "execute", "started_at": "2022-03-29T18:46:09.734793Z", "completed_at": "2022-03-29T18:46:09.734806Z"}], "thread_id": "Thread-1", "execution_time": 0.012056112289428711, "adapter_response": {}, "message": null, "failures": null, "unique_id": "model.smartpill.quickbook_journal_entries"}, {"status": "success", "timing": [{"name": "compile", "started_at": "2022-03-29T18:46:09.736345Z", "completed_at": "2022-03-29T18:46:09.749445Z"}, {"name": "execute", "started_at": "2022-03-29T18:46:09.749722Z", "completed_at": "2022-03-29T18:46:09.749735Z"}], "thread_id": "Thread-1", "execution_time": 0.014128923416137695, "adapter_response": {}, "message": null, "failures": null, "unique_id": "model.smartpill.quickbook_payments"}, {"status": "success", "timing": [{"name": "compile", "started_at": "2022-03-29T18:46:09.751198Z", "completed_at": "2022-03-29T18:46:09.766214Z"}, {"name": "execute", "started_at": "2022-03-29T18:46:09.766490Z", "completed_at": "2022-03-29T18:46:09.766502Z"}], "thread_id": "Thread-1", "execution_time": 0.01603412628173828, "adapter_response": {}, "message": null, "failures": null, "unique_id": "model.smartpill.quickbook_purchases"}, {"status": "success", "timing": [{"name": "compile", "started_at": "2022-03-29T18:46:09.768075Z", "completed_at": "2022-03-29T18:46:09.770499Z"}, {"name": "execute", "started_at": "2022-03-29T18:46:09.770731Z", "completed_at": "2022-03-29T18:46:09.770741Z"}], "thread_id": "Thread-1", "execution_time": 0.003367185592651367, "adapter_response": {}, "message": null, "failures": null, "unique_id": "seed.smartpill.goodpill_events"}, {"status": "success", "timing": [{"name": "compile", "started_at": "2022-03-29T18:46:09.771920Z", "completed_at": "2022-03-29T18:46:09.773962Z"}, {"name": "execute", "started_at": "2022-03-29T18:46:09.774171Z", "completed_at": "2022-03-29T18:46:09.774181Z"}], "thread_id": "Thread-1", "execution_time": 0.002897977828979492, "adapter_response": {}, "message": null, "failures": null, "unique_id": "seed.smartpill.patient_events"}, {"status": "success", "timing": [{"name": "compile", "started_at": "2022-03-29T18:46:09.775289Z", "completed_at": "2022-03-29T18:46:09.794680Z"}, {"name": "execute", "started_at": "2022-03-29T18:46:09.794966Z", "completed_at": "2022-03-29T18:46:09.794981Z"}], "thread_id": "Thread-1", "execution_time": 0.02040696144104004, "adapter_response": {}, "message": null, "failures": null, "unique_id": "model.smartpill.drugs"}, {"status": "success", "timing": [{"name": "compile", "started_at": "2022-03-29T18:46:09.796399Z", "completed_at": "2022-03-29T18:46:09.819364Z"}, {"name": "execute", "started_at": "2022-03-29T18:46:09.819652Z", "completed_at": "2022-03-29T18:46:09.819667Z"}], "thread_id": "Thread-1", "execution_time": 0.02406167984008789, "adapter_response": {}, "message": null, "failures": null, "unique_id": "model.smartpill.order_items_historic"}, {"status": "success", "timing": [{"name": "compile", "started_at": "2022-03-29T18:46:09.821231Z", "completed_at": "2022-03-29T18:46:09.845441Z"}, {"name": "execute", "started_at": "2022-03-29T18:46:09.845727Z", "completed_at": "2022-03-29T18:46:09.845742Z"}], "thread_id": "Thread-1", "execution_time": 0.025305509567260742, "adapter_response": {}, "message": null, "failures": null, "unique_id": "model.smartpill.orders_historic"}, {"status": "success", "timing": [{"name": "compile", "started_at": "2022-03-29T18:46:09.847237Z", "completed_at": "2022-03-29T18:46:09.863870Z"}, {"name": "execute", "started_at": "2022-03-29T18:46:09.864146Z", "completed_at": "2022-03-29T18:46:09.864159Z"}], "thread_id": "Thread-1", "execution_time": 0.017734289169311523, "adapter_response": {}, "message": null, "failures": null, "unique_id": "model.smartpill.locations"}, {"status": "success", "timing": [{"name": "compile", "started_at": "2022-03-29T18:46:09.865498Z", "completed_at": "2022-03-29T18:46:09.877070Z"}, {"name": "execute", "started_at": "2022-03-29T18:46:09.877334Z", "completed_at": "2022-03-29T18:46:09.877348Z"}], "thread_id": "Thread-1", "execution_time": 0.012569665908813477, "adapter_response": {}, "message": null, "failures": null, "unique_id": "model.smartpill.pharmacies"}, {"status": "success", "timing": [{"name": "compile", "started_at": "2022-03-29T18:46:09.878561Z", "completed_at": "2022-03-29T18:46:09.899104Z"}, {"name": "execute", "started_at": "2022-03-29T18:46:09.899383Z", "completed_at": "2022-03-29T18:46:09.899397Z"}], "thread_id": "Thread-1", "execution_time": 0.021577119827270508, "adapter_response": {}, "message": null, "failures": null, "unique_id": "model.smartpill.patients"}, {"status": "success", "timing": [{"name": "compile", "started_at": "2022-03-29T18:46:09.900689Z", "completed_at": "2022-03-29T18:46:09.909718Z"}, {"name": "execute", "started_at": "2022-03-29T18:46:09.909974Z", "completed_at": "2022-03-29T18:46:09.909986Z"}], "thread_id": "Thread-1", "execution_time": 0.010061502456665039, "adapter_response": {}, "message": null, "failures": null, "unique_id": "model.smartpill.clinics"}, {"status": "success", "timing": [{"name": "compile", "started_at": "2022-03-29T18:46:09.911144Z", "completed_at": "2022-03-29T18:46:09.922533Z"}, {"name": "execute", "started_at": "2022-03-29T18:46:09.922802Z", "completed_at": "2022-03-29T18:46:09.922815Z"}], "thread_id": "Thread-1", "execution_time": 0.012368202209472656, "adapter_response": {}, "message": null, "failures": null, "unique_id": "model.smartpill.providers"}, {"status": "success", "timing": [{"name": "compile", "started_at": "2022-03-29T18:46:09.923999Z", "completed_at": "2022-03-29T18:46:09.975617Z"}, {"name": "execute", "started_at": "2022-03-29T18:46:09.975915Z", "completed_at": "2022-03-29T18:46:09.975930Z"}], "thread_id": "Thread-1", "execution_time": 0.052681684494018555, "adapter_response": {}, "message": null, "failures": null, "unique_id": "model.smartpill.rxs_historic"}, {"status": "success", "timing": [{"name": "compile", "started_at": "2022-03-29T18:46:09.982931Z", "completed_at": "2022-03-29T18:46:09.986715Z"}, {"name": "execute", "started_at": "2022-03-29T18:46:09.987048Z", "completed_at": "2022-03-29T18:46:09.987059Z"}], "thread_id": "Thread-1", "execution_time": 0.0047795772552490234, "adapter_response": {}, "message": null, "failures": null, "unique_id": "model.smartpill.quickbook_accounts_top_level"}, {"status": "success", "timing": [{"name": "compile", "started_at": "2022-03-29T18:46:09.988233Z", "completed_at": "2022-03-29T18:46:09.995594Z"}, {"name": "execute", "started_at": "2022-03-29T18:46:09.995854Z", "completed_at": "2022-03-29T18:46:09.995867Z"}], "thread_id": "Thread-1", "execution_time": 0.008371591567993164, "adapter_response": {}, "message": null, "failures": null, "unique_id": "test.smartpill.not_null_quickbook_accounts__hash_id.143e025811"}, {"status": "success", "timing": [{"name": "compile", "started_at": "2022-03-29T18:46:09.997131Z", "completed_at": "2022-03-29T18:46:10.001543Z"}, {"name": "execute", "started_at": "2022-03-29T18:46:10.001788Z", "completed_at": "2022-03-29T18:46:10.001799Z"}], "thread_id": "Thread-1", "execution_time": 0.005330324172973633, "adapter_response": {}, "message": null, "failures": null, "unique_id": "test.smartpill.not_null_quickbook_accounts_balance.1f29272f5e"}, {"status": "success", "timing": [{"name": "compile", "started_at": "2022-03-29T18:46:10.002959Z", "completed_at": "2022-03-29T18:46:10.008331Z"}, {"name": "execute", "started_at": "2022-03-29T18:46:10.008655Z", "completed_at": "2022-03-29T18:46:10.008668Z"}], "thread_id": "Thread-1", "execution_time": 0.0063800811767578125, "adapter_response": {}, "message": null, "failures": null, "unique_id": "test.smartpill.not_null_quickbook_accounts_created_at.3c095347ed"}, {"status": "success", "timing": [{"name": "compile", "started_at": "2022-03-29T18:46:10.009870Z", "completed_at": "2022-03-29T18:46:10.016833Z"}, {"name": "execute", "started_at": "2022-03-29T18:46:10.017114Z", "completed_at": "2022-03-29T18:46:10.017126Z"}], "thread_id": "Thread-1", "execution_time": 0.007948160171508789, "adapter_response": {}, "message": null, "failures": null, "unique_id": "test.smartpill.not_null_quickbook_accounts_id.a12b25cd25"}, {"status": "success", "timing": [{"name": "compile", "started_at": "2022-03-29T18:46:10.018364Z", "completed_at": "2022-03-29T18:46:10.022934Z"}, {"name": "execute", "started_at": "2022-03-29T18:46:10.023179Z", "completed_at": "2022-03-29T18:46:10.023190Z"}], "thread_id": "Thread-1", "execution_time": 0.0054972171783447266, "adapter_response": {}, "message": null, "failures": null, "unique_id": "test.smartpill.not_null_quickbook_accounts_updated_at.a6113a6333"}, {"status": "success", "timing": [{"name": "compile", "started_at": "2022-03-29T18:46:10.024435Z", "completed_at": "2022-03-29T18:46:10.030687Z"}, {"name": "execute", "started_at": "2022-03-29T18:46:10.030957Z", "completed_at": "2022-03-29T18:46:10.030971Z"}], "thread_id": "Thread-1", "execution_time": 0.007288455963134766, "adapter_response": {}, "message": null, "failures": null, "unique_id": "test.smartpill.relationships_quickbook_accounts_parent_account_id__id__ref_quickbook_accounts_.1ef3f81866"}, {"status": "success", "timing": [{"name": "compile", "started_at": "2022-03-29T18:46:10.032225Z", "completed_at": "2022-03-29T18:46:10.040126Z"}, {"name": "execute", "started_at": "2022-03-29T18:46:10.040471Z", "completed_at": "2022-03-29T18:46:10.040484Z"}], "thread_id": "Thread-1", "execution_time": 0.008991241455078125, "adapter_response": {}, "message": null, "failures": null, "unique_id": "test.smartpill.unique_quickbook_accounts__hash_id.46960e991f"}, {"status": "success", "timing": [{"name": "compile", "started_at": "2022-03-29T18:46:10.047198Z", "completed_at": "2022-03-29T18:46:10.055781Z"}, {"name": "execute", "started_at": "2022-03-29T18:46:10.056048Z", "completed_at": "2022-03-29T18:46:10.056060Z"}], "thread_id": "Thread-1", "execution_time": 0.009545564651489258, "adapter_response": {}, "message": null, "failures": null, "unique_id": "model.smartpill.quickbook_bill_payments_lines"}, {"status": "success", "timing": [{"name": "compile", "started_at": "2022-03-29T18:46:10.057729Z", "completed_at": "2022-03-29T18:46:10.062605Z"}, {"name": "execute", "started_at": "2022-03-29T18:46:10.062859Z", "completed_at": "2022-03-29T18:46:10.062871Z"}], "thread_id": "Thread-1", "execution_time": 0.006121397018432617, "adapter_response": {}, "message": null, "failures": null, "unique_id": "test.smartpill.not_null_quickbook_bill_payments__hash_id.fd526f8604"}, {"status": "success", "timing": [{"name": "compile", "started_at": "2022-03-29T18:46:10.064057Z", "completed_at": "2022-03-29T18:46:10.068734Z"}, {"name": "execute", "started_at": "2022-03-29T18:46:10.069005Z", "completed_at": "2022-03-29T18:46:10.069017Z"}], "thread_id": "Thread-1", "execution_time": 0.005623340606689453, "adapter_response": {}, "message": null, "failures": null, "unique_id": "test.smartpill.not_null_quickbook_bill_payments_created_at.0377523a21"}, {"status": "success", "timing": [{"name": "compile", "started_at": "2022-03-29T18:46:10.070519Z", "completed_at": "2022-03-29T18:46:10.077147Z"}, {"name": "execute", "started_at": "2022-03-29T18:46:10.077445Z", "completed_at": "2022-03-29T18:46:10.077458Z"}], "thread_id": "Thread-1", "execution_time": 0.007839679718017578, "adapter_response": {}, "message": null, "failures": null, "unique_id": "test.smartpill.not_null_quickbook_bill_payments_id.1499a08374"}, {"status": "success", "timing": [{"name": "compile", "started_at": "2022-03-29T18:46:10.078581Z", "completed_at": "2022-03-29T18:46:10.083311Z"}, {"name": "execute", "started_at": "2022-03-29T18:46:10.083569Z", "completed_at": "2022-03-29T18:46:10.083582Z"}], "thread_id": "Thread-1", "execution_time": 0.005656003952026367, "adapter_response": {}, "message": null, "failures": null, "unique_id": "test.smartpill.not_null_quickbook_bill_payments_updated_at.2c9cbc0ebd"}, {"status": "success", "timing": [{"name": "compile", "started_at": "2022-03-29T18:46:10.084780Z", "completed_at": "2022-03-29T18:46:10.089816Z"}, {"name": "execute", "started_at": "2022-03-29T18:46:10.090078Z", "completed_at": "2022-03-29T18:46:10.090091Z"}], "thread_id": "Thread-1", "execution_time": 0.006060600280761719, "adapter_response": {}, "message": null, "failures": null, "unique_id": "test.smartpill.unique_quickbook_bill_payments__hash_id.9710f17760"}, {"status": "success", "timing": [{"name": "compile", "started_at": "2022-03-29T18:46:10.091304Z", "completed_at": "2022-03-29T18:46:10.109117Z"}, {"name": "execute", "started_at": "2022-03-29T18:46:10.109399Z", "completed_at": "2022-03-29T18:46:10.109412Z"}], "thread_id": "Thread-1", "execution_time": 0.018799781799316406, "adapter_response": {}, "message": null, "failures": null, "unique_id": "model.smartpill.quickbook_bills_lines"}, {"status": "success", "timing": [{"name": "compile", "started_at": "2022-03-29T18:46:10.110809Z", "completed_at": "2022-03-29T18:46:10.116072Z"}, {"name": "execute", "started_at": "2022-03-29T18:46:10.116336Z", "completed_at": "2022-03-29T18:46:10.116349Z"}], "thread_id": "Thread-1", "execution_time": 0.0063533782958984375, "adapter_response": {}, "message": null, "failures": null, "unique_id": "test.smartpill.not_null_quickbook_bills__hash_id.f6bb81e956"}, {"status": "success", "timing": [{"name": "compile", "started_at": "2022-03-29T18:46:10.117602Z", "completed_at": "2022-03-29T18:46:10.122344Z"}, {"name": "execute", "started_at": "2022-03-29T18:46:10.122606Z", "completed_at": "2022-03-29T18:46:10.122618Z"}], "thread_id": "Thread-1", "execution_time": 0.0057353973388671875, "adapter_response": {}, "message": null, "failures": null, "unique_id": "test.smartpill.not_null_quickbook_bills_created_at.e161c96e40"}, {"status": "success", "timing": [{"name": "compile", "started_at": "2022-03-29T18:46:10.123750Z", "completed_at": "2022-03-29T18:46:10.130194Z"}, {"name": "execute", "started_at": "2022-03-29T18:46:10.130463Z", "completed_at": "2022-03-29T18:46:10.130475Z"}], "thread_id": "Thread-1", "execution_time": 0.007410526275634766, "adapter_response": {}, "message": null, "failures": null, "unique_id": "test.smartpill.not_null_quickbook_bills_id.ade9b1b0e8"}, {"status": "success", "timing": [{"name": "compile", "started_at": "2022-03-29T18:46:10.131639Z", "completed_at": "2022-03-29T18:46:10.136373Z"}, {"name": "execute", "started_at": "2022-03-29T18:46:10.136706Z", "completed_at": "2022-03-29T18:46:10.136718Z"}], "thread_id": "Thread-1", "execution_time": 0.005742311477661133, "adapter_response": {}, "message": null, "failures": null, "unique_id": "test.smartpill.not_null_quickbook_bills_updated_at.9b89152a35"}, {"status": "success", "timing": [{"name": "compile", "started_at": "2022-03-29T18:46:10.137835Z", "completed_at": "2022-03-29T18:46:10.142880Z"}, {"name": "execute", "started_at": "2022-03-29T18:46:10.143146Z", "completed_at": "2022-03-29T18:46:10.143159Z"}], "thread_id": "Thread-1", "execution_time": 0.005986690521240234, "adapter_response": {}, "message": null, "failures": null, "unique_id": "test.smartpill.unique_quickbook_bills__hash_id.dc216c74e4"}, {"status": "success", "timing": [{"name": "compile", "started_at": "2022-03-29T18:46:10.144278Z", "completed_at": "2022-03-29T18:46:10.149174Z"}, {"name": "execute", "started_at": "2022-03-29T18:46:10.149435Z", "completed_at": "2022-03-29T18:46:10.149447Z"}], "thread_id": "Thread-1", "execution_time": 0.005825519561767578, "adapter_response": {}, "message": null, "failures": null, "unique_id": "test.smartpill.not_null_quickbook_classes__hash_id.ce90f05ef4"}, {"status": "success", "timing": [{"name": "compile", "started_at": "2022-03-29T18:46:10.150558Z", "completed_at": "2022-03-29T18:46:10.155352Z"}, {"name": "execute", "started_at": "2022-03-29T18:46:10.155613Z", "completed_at": "2022-03-29T18:46:10.155627Z"}], "thread_id": "Thread-1", "execution_time": 0.0057239532470703125, "adapter_response": {}, "message": null, "failures": null, "unique_id": "test.smartpill.not_null_quickbook_classes_created_at.8849d47908"}, {"status": "success", "timing": [{"name": "compile", "started_at": "2022-03-29T18:46:10.156808Z", "completed_at": "2022-03-29T18:46:10.161552Z"}, {"name": "execute", "started_at": "2022-03-29T18:46:10.161809Z", "completed_at": "2022-03-29T18:46:10.161821Z"}], "thread_id": "Thread-1", "execution_time": 0.005764484405517578, "adapter_response": {}, "message": null, "failures": null, "unique_id": "test.smartpill.not_null_quickbook_classes_id.341dc94c0b"}, {"status": "success", "timing": [{"name": "compile", "started_at": "2022-03-29T18:46:10.163064Z", "completed_at": "2022-03-29T18:46:10.167984Z"}, {"name": "execute", "started_at": "2022-03-29T18:46:10.168241Z", "completed_at": "2022-03-29T18:46:10.168253Z"}], "thread_id": "Thread-1", "execution_time": 0.006000995635986328, "adapter_response": {}, "message": null, "failures": null, "unique_id": "test.smartpill.not_null_quickbook_classes_updated_at.6c3f5bf01f"}, {"status": "success", "timing": [{"name": "compile", "started_at": "2022-03-29T18:46:10.169438Z", "completed_at": "2022-03-29T18:46:10.174060Z"}, {"name": "execute", "started_at": "2022-03-29T18:46:10.174307Z", "completed_at": "2022-03-29T18:46:10.174317Z"}], "thread_id": "Thread-1", "execution_time": 0.005517005920410156, "adapter_response": {}, "message": null, "failures": null, "unique_id": "test.smartpill.unique_quickbook_classes__hash_id.767e20cd2e"}, {"status": "success", "timing": [{"name": "compile", "started_at": "2022-03-29T18:46:10.175409Z", "completed_at": "2022-03-29T18:46:10.181685Z"}, {"name": "execute", "started_at": "2022-03-29T18:46:10.181946Z", "completed_at": "2022-03-29T18:46:10.181958Z"}], "thread_id": "Thread-1", "execution_time": 0.007195234298706055, "adapter_response": {}, "message": null, "failures": null, "unique_id": "test.smartpill.not_null_quickbook_customers__hash_id.bee7bb4912"}, {"status": "success", "timing": [{"name": "compile", "started_at": "2022-03-29T18:46:10.183098Z", "completed_at": "2022-03-29T18:46:10.188434Z"}, {"name": "execute", "started_at": "2022-03-29T18:46:10.188721Z", "completed_at": "2022-03-29T18:46:10.188732Z"}], "thread_id": "Thread-1", "execution_time": 0.006309986114501953, "adapter_response": {}, "message": null, "failures": null, "unique_id": "test.smartpill.not_null_quickbook_customers_created_at.382d28fb34"}, {"status": "success", "timing": [{"name": "compile", "started_at": "2022-03-29T18:46:10.189810Z", "completed_at": "2022-03-29T18:46:10.194363Z"}, {"name": "execute", "started_at": "2022-03-29T18:46:10.194610Z", "completed_at": "2022-03-29T18:46:10.194621Z"}], "thread_id": "Thread-1", "execution_time": 0.005444765090942383, "adapter_response": {}, "message": null, "failures": null, "unique_id": "test.smartpill.not_null_quickbook_customers_id.96bc4b1497"}, {"status": "success", "timing": [{"name": "compile", "started_at": "2022-03-29T18:46:10.195698Z", "completed_at": "2022-03-29T18:46:10.200598Z"}, {"name": "execute", "started_at": "2022-03-29T18:46:10.200883Z", "completed_at": "2022-03-29T18:46:10.200895Z"}], "thread_id": "Thread-1", "execution_time": 0.005845069885253906, "adapter_response": {}, "message": null, "failures": null, "unique_id": "test.smartpill.not_null_quickbook_customers_updated_at.4c4939f533"}, {"status": "success", "timing": [{"name": "compile", "started_at": "2022-03-29T18:46:10.201997Z", "completed_at": "2022-03-29T18:46:10.206836Z"}, {"name": "execute", "started_at": "2022-03-29T18:46:10.207097Z", "completed_at": "2022-03-29T18:46:10.207109Z"}], "thread_id": "Thread-1", "execution_time": 0.0057621002197265625, "adapter_response": {}, "message": null, "failures": null, "unique_id": "test.smartpill.unique_quickbook_customers__hash_id.f980d531c9"}, {"status": "success", "timing": [{"name": "compile", "started_at": "2022-03-29T18:46:10.208583Z", "completed_at": "2022-03-29T18:46:10.220863Z"}, {"name": "execute", "started_at": "2022-03-29T18:46:10.221121Z", "completed_at": "2022-03-29T18:46:10.221132Z"}], "thread_id": "Thread-1", "execution_time": 0.01342320442199707, "adapter_response": {}, "message": null, "failures": null, "unique_id": "model.smartpill.quickbook_deposits_lines"}, {"status": "success", "timing": [{"name": "compile", "started_at": "2022-03-29T18:46:10.222456Z", "completed_at": "2022-03-29T18:46:10.227137Z"}, {"name": "execute", "started_at": "2022-03-29T18:46:10.227381Z", "completed_at": "2022-03-29T18:46:10.227393Z"}], "thread_id": "Thread-1", "execution_time": 0.00559687614440918, "adapter_response": {}, "message": null, "failures": null, "unique_id": "test.smartpill.not_null_quickbook_deposits__hash_id.5e9f31c2c7"}, {"status": "success", "timing": [{"name": "compile", "started_at": "2022-03-29T18:46:10.228703Z", "completed_at": "2022-03-29T18:46:10.235100Z"}, {"name": "execute", "started_at": "2022-03-29T18:46:10.235361Z", "completed_at": "2022-03-29T18:46:10.235375Z"}], "thread_id": "Thread-1", "execution_time": 0.007601737976074219, "adapter_response": {}, "message": null, "failures": null, "unique_id": "test.smartpill.not_null_quickbook_deposits_created_at.0e50747340"}, {"status": "success", "timing": [{"name": "compile", "started_at": "2022-03-29T18:46:10.236644Z", "completed_at": "2022-03-29T18:46:10.241768Z"}, {"name": "execute", "started_at": "2022-03-29T18:46:10.242025Z", "completed_at": "2022-03-29T18:46:10.242038Z"}], "thread_id": "Thread-1", "execution_time": 0.00616145133972168, "adapter_response": {}, "message": null, "failures": null, "unique_id": "test.smartpill.not_null_quickbook_deposits_id.d999e6aa7a"}, {"status": "success", "timing": [{"name": "compile", "started_at": "2022-03-29T18:46:10.243129Z", "completed_at": "2022-03-29T18:46:10.247629Z"}, {"name": "execute", "started_at": "2022-03-29T18:46:10.248027Z", "completed_at": "2022-03-29T18:46:10.248042Z"}], "thread_id": "Thread-1", "execution_time": 0.005568265914916992, "adapter_response": {}, "message": null, "failures": null, "unique_id": "test.smartpill.not_null_quickbook_deposits_updated_at.8c397fa724"}, {"status": "success", "timing": [{"name": "compile", "started_at": "2022-03-29T18:46:10.249200Z", "completed_at": "2022-03-29T18:46:10.255343Z"}, {"name": "execute", "started_at": "2022-03-29T18:46:10.255595Z", "completed_at": "2022-03-29T18:46:10.255607Z"}], "thread_id": "Thread-1", "execution_time": 0.0070607662200927734, "adapter_response": {}, "message": null, "failures": null, "unique_id": "test.smartpill.relationships_quickbook_deposits_account_id__id__ref_quickbook_accounts_.af52410005"}, {"status": "success", "timing": [{"name": "compile", "started_at": "2022-03-29T18:46:10.256792Z", "completed_at": "2022-03-29T18:46:10.261209Z"}, {"name": "execute", "started_at": "2022-03-29T18:46:10.261454Z", "completed_at": "2022-03-29T18:46:10.261465Z"}], "thread_id": "Thread-1", "execution_time": 0.0054094791412353516, "adapter_response": {}, "message": null, "failures": null, "unique_id": "test.smartpill.unique_quickbook_deposits__hash_id.c3b47a62c6"}, {"status": "success", "timing": [{"name": "compile", "started_at": "2022-03-29T18:46:10.262533Z", "completed_at": "2022-03-29T18:46:10.277546Z"}, {"name": "execute", "started_at": "2022-03-29T18:46:10.277809Z", "completed_at": "2022-03-29T18:46:10.277822Z"}], "thread_id": "Thread-1", "execution_time": 0.015949487686157227, "adapter_response": {}, "message": null, "failures": null, "unique_id": "model.smartpill.quickbook_invoices_lines"}, {"status": "success", "timing": [{"name": "compile", "started_at": "2022-03-29T18:46:10.279284Z", "completed_at": "2022-03-29T18:46:10.295021Z"}, {"name": "execute", "started_at": "2022-03-29T18:46:10.295277Z", "completed_at": "2022-03-29T18:46:10.295288Z"}], "thread_id": "Thread-1", "execution_time": 0.016780853271484375, "adapter_response": {}, "message": null, "failures": null, "unique_id": "model.smartpill.quickbook_journal_entries_lines"}, {"status": "success", "timing": [{"name": "compile", "started_at": "2022-03-29T18:46:10.296816Z", "completed_at": "2022-03-29T18:46:10.360918Z"}, {"name": "execute", "started_at": "2022-03-29T18:46:10.361188Z", "completed_at": "2022-03-29T18:46:10.361201Z"}], "thread_id": "Thread-1", "execution_time": 0.06518983840942383, "adapter_response": {}, "message": null, "failures": null, "unique_id": "test.smartpill.not_null_quickbook_journal_entries__hash_id.9c0aa8856e"}, {"status": "success", "timing": [{"name": "compile", "started_at": "2022-03-29T18:46:10.362313Z", "completed_at": "2022-03-29T18:46:10.368076Z"}, {"name": "execute", "started_at": "2022-03-29T18:46:10.368365Z", "completed_at": "2022-03-29T18:46:10.368377Z"}], "thread_id": "Thread-1", "execution_time": 0.006773471832275391, "adapter_response": {}, "message": null, "failures": null, "unique_id": "test.smartpill.not_null_quickbook_journal_entries_created_at.afe29e0363"}, {"status": "success", "timing": [{"name": "compile", "started_at": "2022-03-29T18:46:10.369513Z", "completed_at": "2022-03-29T18:46:10.374019Z"}, {"name": "execute", "started_at": "2022-03-29T18:46:10.374262Z", "completed_at": "2022-03-29T18:46:10.374272Z"}], "thread_id": "Thread-1", "execution_time": 0.005420684814453125, "adapter_response": {}, "message": null, "failures": null, "unique_id": "test.smartpill.not_null_quickbook_journal_entries_id.49dc1d7aaa"}, {"status": "success", "timing": [{"name": "compile", "started_at": "2022-03-29T18:46:10.375356Z", "completed_at": "2022-03-29T18:46:10.379714Z"}, {"name": "execute", "started_at": "2022-03-29T18:46:10.379961Z", "completed_at": "2022-03-29T18:46:10.379972Z"}], "thread_id": "Thread-1", "execution_time": 0.0052449703216552734, "adapter_response": {}, "message": null, "failures": null, "unique_id": "test.smartpill.not_null_quickbook_journal_entries_updated_at.54a9ed1f87"}, {"status": "success", "timing": [{"name": "compile", "started_at": "2022-03-29T18:46:10.381111Z", "completed_at": "2022-03-29T18:46:10.385663Z"}, {"name": "execute", "started_at": "2022-03-29T18:46:10.385924Z", "completed_at": "2022-03-29T18:46:10.385935Z"}], "thread_id": "Thread-1", "execution_time": 0.0056149959564208984, "adapter_response": {}, "message": null, "failures": null, "unique_id": "test.smartpill.unique_quickbook_journal_entries__hash_id.badff0ae61"}, {"status": "success", "timing": [{"name": "compile", "started_at": "2022-03-29T18:46:10.392862Z", "completed_at": "2022-03-29T18:46:10.409774Z"}, {"name": "execute", "started_at": "2022-03-29T18:46:10.410040Z", "completed_at": "2022-03-29T18:46:10.410051Z"}], "thread_id": "Thread-1", "execution_time": 0.017868995666503906, "adapter_response": {}, "message": null, "failures": null, "unique_id": "model.smartpill.quickbook_purchases_lines"}, {"status": "success", "timing": [{"name": "compile", "started_at": "2022-03-29T18:46:10.411404Z", "completed_at": "2022-03-29T18:46:10.416061Z"}, {"name": "execute", "started_at": "2022-03-29T18:46:10.416314Z", "completed_at": "2022-03-29T18:46:10.416326Z"}], "thread_id": "Thread-1", "execution_time": 0.0056302547454833984, "adapter_response": {}, "message": null, "failures": null, "unique_id": "test.smartpill.not_null_quickbook_purchases__hash_id.60e376006a"}, {"status": "success", "timing": [{"name": "compile", "started_at": "2022-03-29T18:46:10.417486Z", "completed_at": "2022-03-29T18:46:10.422100Z"}, {"name": "execute", "started_at": "2022-03-29T18:46:10.422340Z", "completed_at": "2022-03-29T18:46:10.422351Z"}], "thread_id": "Thread-1", "execution_time": 0.005525827407836914, "adapter_response": {}, "message": null, "failures": null, "unique_id": "test.smartpill.not_null_quickbook_purchases_created_at.5396da13c3"}, {"status": "success", "timing": [{"name": "compile", "started_at": "2022-03-29T18:46:10.423410Z", "completed_at": "2022-03-29T18:46:10.427795Z"}, {"name": "execute", "started_at": "2022-03-29T18:46:10.428037Z", "completed_at": "2022-03-29T18:46:10.428049Z"}], "thread_id": "Thread-1", "execution_time": 0.005274534225463867, "adapter_response": {}, "message": null, "failures": null, "unique_id": "test.smartpill.not_null_quickbook_purchases_id.b59acb53aa"}, {"status": "success", "timing": [{"name": "compile", "started_at": "2022-03-29T18:46:10.429168Z", "completed_at": "2022-03-29T18:46:10.433723Z"}, {"name": "execute", "started_at": "2022-03-29T18:46:10.433967Z", "completed_at": "2022-03-29T18:46:10.433978Z"}], "thread_id": "Thread-1", "execution_time": 0.005446195602416992, "adapter_response": {}, "message": null, "failures": null, "unique_id": "test.smartpill.not_null_quickbook_purchases_updated_at.7f3c1ad27f"}, {"status": "success", "timing": [{"name": "compile", "started_at": "2022-03-29T18:46:10.435046Z", "completed_at": "2022-03-29T18:46:10.441175Z"}, {"name": "execute", "started_at": "2022-03-29T18:46:10.441562Z", "completed_at": "2022-03-29T18:46:10.441575Z"}], "thread_id": "Thread-1", "execution_time": 0.007200002670288086, "adapter_response": {}, "message": null, "failures": null, "unique_id": "test.smartpill.relationships_quickbook_purchases_account_id__id__ref_quickbook_accounts_.de403dfc25"}, {"status": "success", "timing": [{"name": "compile", "started_at": "2022-03-29T18:46:10.442683Z", "completed_at": "2022-03-29T18:46:10.447212Z"}, {"name": "execute", "started_at": "2022-03-29T18:46:10.447462Z", "completed_at": "2022-03-29T18:46:10.447475Z"}], "thread_id": "Thread-1", "execution_time": 0.00544428825378418, "adapter_response": {}, "message": null, "failures": null, "unique_id": "test.smartpill.unique_quickbook_purchases__hash_id.895322ff1b"}, {"status": "success", "timing": [{"name": "compile", "started_at": "2022-03-29T18:46:11.752779Z", "completed_at": "2022-03-29T18:46:11.759685Z"}, {"name": "execute", "started_at": "2022-03-29T18:46:11.759957Z", "completed_at": "2022-03-29T18:46:11.759970Z"}], "thread_id": "Thread-1", "execution_time": 0.008237123489379883, "adapter_response": {}, "message": null, "failures": null, "unique_id": "test.smartpill.relationships_quickbook_bill_payments_lines__bill_payment_hash_id___hash_id__ref_quickbook_bill_payments_.05c60eabd2"}, {"status": "success", "timing": [{"name": "compile", "started_at": "2022-03-29T18:46:11.761543Z", "completed_at": "2022-03-29T18:46:11.768173Z"}, {"name": "execute", "started_at": "2022-03-29T18:46:11.768511Z", "completed_at": "2022-03-29T18:46:11.768527Z"}], "thread_id": "Thread-1", "execution_time": 0.008040904998779297, "adapter_response": {}, "message": null, "failures": null, "unique_id": "test.smartpill.relationships_quickbook_bill_payments_lines_bill_id__id__ref_quickbook_bills_.74ec54787f"}, {"status": "success", "timing": [{"name": "compile", "started_at": "2022-03-29T18:46:11.769669Z", "completed_at": "2022-03-29T18:46:11.775738Z"}, {"name": "execute", "started_at": "2022-03-29T18:46:11.775995Z", "completed_at": "2022-03-29T18:46:11.776008Z"}], "thread_id": "Thread-1", "execution_time": 0.007014036178588867, "adapter_response": {}, "message": null, "failures": null, "unique_id": "test.smartpill.relationships_quickbook_bill_payments_lines_bill_payment_id__id__ref_quickbook_bills_.940be60147"}, {"status": "success", "timing": [{"name": "compile", "started_at": "2022-03-29T18:46:11.777677Z", "completed_at": "2022-03-29T18:46:11.783858Z"}, {"name": "execute", "started_at": "2022-03-29T18:46:11.784112Z", "completed_at": "2022-03-29T18:46:11.784124Z"}], "thread_id": "Thread-1", "execution_time": 0.007161617279052734, "adapter_response": {}, "message": null, "failures": null, "unique_id": "test.smartpill.relationships_quickbook_bill_payments_lines_deposit_id__id__ref_quickbook_deposits_.7613bf6d2c"}, {"status": "success", "timing": [{"name": "compile", "started_at": "2022-03-29T18:46:11.785301Z", "completed_at": "2022-03-29T18:46:11.791641Z"}, {"name": "execute", "started_at": "2022-03-29T18:46:11.791904Z", "completed_at": "2022-03-29T18:46:11.791917Z"}], "thread_id": "Thread-1", "execution_time": 0.0072710514068603516, "adapter_response": {}, "message": null, "failures": null, "unique_id": "test.smartpill.relationships_quickbook_bill_payments_lines_journal_entry_id__id__ref_quickbook_journal_entries_.6a0243be78"}, {"status": "success", "timing": [{"name": "compile", "started_at": "2022-03-29T18:46:11.799158Z", "completed_at": "2022-03-29T18:46:11.807253Z"}, {"name": "execute", "started_at": "2022-03-29T18:46:11.807511Z", "completed_at": "2022-03-29T18:46:11.807525Z"}], "thread_id": "Thread-1", "execution_time": 0.00902414321899414, "adapter_response": {}, "message": null, "failures": null, "unique_id": "test.smartpill.relationships_quickbook_bills_lines__bill_hash_id___hash_id__ref_quickbook_bills_.55baa33281"}, {"status": "success", "timing": [{"name": "compile", "started_at": "2022-03-29T18:46:11.809585Z", "completed_at": "2022-03-29T18:46:11.816170Z"}, {"name": "execute", "started_at": "2022-03-29T18:46:11.816444Z", "completed_at": "2022-03-29T18:46:11.816461Z"}], "thread_id": "Thread-1", "execution_time": 0.007594108581542969, "adapter_response": {}, "message": null, "failures": null, "unique_id": "test.smartpill.relationships_quickbook_bills_lines_bill_id__id__ref_quickbook_bills_.1c0ea3fbc9"}, {"status": "success", "timing": [{"name": "compile", "started_at": "2022-03-29T18:46:11.825234Z", "completed_at": "2022-03-29T18:46:11.831846Z"}, {"name": "execute", "started_at": "2022-03-29T18:46:11.832130Z", "completed_at": "2022-03-29T18:46:11.832143Z"}], "thread_id": "Thread-1", "execution_time": 0.00764012336730957, "adapter_response": {}, "message": null, "failures": null, "unique_id": "test.smartpill.relationships_quickbook_deposits_lines__deposit_hash_id___hash_id__ref_quickbook_deposits_.f387c86a00"}, {"status": "success", "timing": [{"name": "compile", "started_at": "2022-03-29T18:46:11.833278Z", "completed_at": "2022-03-29T18:46:11.839468Z"}, {"name": "execute", "started_at": "2022-03-29T18:46:11.839766Z", "completed_at": "2022-03-29T18:46:11.839780Z"}], "thread_id": "Thread-1", "execution_time": 0.007164478302001953, "adapter_response": {}, "message": null, "failures": null, "unique_id": "test.smartpill.relationships_quickbook_deposits_lines_account_id__id__ref_quickbook_accounts_.3da227e20f"}, {"status": "success", "timing": [{"name": "compile", "started_at": "2022-03-29T18:46:11.840996Z", "completed_at": "2022-03-29T18:46:11.847207Z"}, {"name": "execute", "started_at": "2022-03-29T18:46:11.847461Z", "completed_at": "2022-03-29T18:46:11.847474Z"}], "thread_id": "Thread-1", "execution_time": 0.007161617279052734, "adapter_response": {}, "message": null, "failures": null, "unique_id": "test.smartpill.relationships_quickbook_deposits_lines_class_id__id__ref_quickbook_classes_.9401d802d8"}, {"status": "success", "timing": [{"name": "compile", "started_at": "2022-03-29T18:46:11.848666Z", "completed_at": "2022-03-29T18:46:11.855228Z"}, {"name": "execute", "started_at": "2022-03-29T18:46:11.855517Z", "completed_at": "2022-03-29T18:46:11.855529Z"}], "thread_id": "Thread-1", "execution_time": 0.007570981979370117, "adapter_response": {}, "message": null, "failures": null, "unique_id": "test.smartpill.relationships_quickbook_deposits_lines_customer_id__id__ref_quickbook_customers_.b7dfd585c3"}, {"status": "success", "timing": [{"name": "compile", "started_at": "2022-03-29T18:46:11.873248Z", "completed_at": "2022-03-29T18:46:11.881356Z"}, {"name": "execute", "started_at": "2022-03-29T18:46:11.881687Z", "completed_at": "2022-03-29T18:46:11.881701Z"}], "thread_id": "Thread-1", "execution_time": 0.011655330657958984, "adapter_response": {}, "message": null, "failures": null, "unique_id": "test.smartpill.relationships_quickbook_journal_entries_lines__journal_entry_hash_id___hash_id__ref_quickbook_journal_entries_.1ab076db90"}, {"status": "success", "timing": [{"name": "compile", "started_at": "2022-03-29T18:46:11.882878Z", "completed_at": "2022-03-29T18:46:11.889470Z"}, {"name": "execute", "started_at": "2022-03-29T18:46:11.889725Z", "completed_at": "2022-03-29T18:46:11.889737Z"}], "thread_id": "Thread-1", "execution_time": 0.007529020309448242, "adapter_response": {}, "message": null, "failures": null, "unique_id": "test.smartpill.relationships_quickbook_journal_entries_lines_account_id__id__ref_quickbook_accounts_.a3212fffc2"}, {"status": "success", "timing": [{"name": "compile", "started_at": "2022-03-29T18:46:11.890891Z", "completed_at": "2022-03-29T18:46:11.896756Z"}, {"name": "execute", "started_at": "2022-03-29T18:46:11.896999Z", "completed_at": "2022-03-29T18:46:11.897011Z"}], "thread_id": "Thread-1", "execution_time": 0.0067882537841796875, "adapter_response": {}, "message": null, "failures": null, "unique_id": "test.smartpill.relationships_quickbook_journal_entries_lines_class_id__id__ref_quickbook_classes_.7feeb4e66b"}, {"status": "success", "timing": [{"name": "compile", "started_at": "2022-03-29T18:46:11.898136Z", "completed_at": "2022-03-29T18:46:11.904798Z"}, {"name": "execute", "started_at": "2022-03-29T18:46:11.905058Z", "completed_at": "2022-03-29T18:46:11.905070Z"}], "thread_id": "Thread-1", "execution_time": 0.00760340690612793, "adapter_response": {}, "message": null, "failures": null, "unique_id": "test.smartpill.relationships_quickbook_journal_entries_lines_customer_id__id__ref_quickbook_customers_.689ebbf3f6"}, {"status": "success", "timing": [{"name": "compile", "started_at": "2022-03-29T18:46:11.912334Z", "completed_at": "2022-03-29T18:46:11.918761Z"}, {"name": "execute", "started_at": "2022-03-29T18:46:11.919003Z", "completed_at": "2022-03-29T18:46:11.919015Z"}], "thread_id": "Thread-1", "execution_time": 0.00734257698059082, "adapter_response": {}, "message": null, "failures": null, "unique_id": "test.smartpill.relationships_quickbook_purchases_lines__purchase_hash_id___hash_id__ref_quickbook_purchases_.05bef6f0f4"}, {"status": "success", "timing": [{"name": "compile", "started_at": "2022-03-29T18:46:11.920141Z", "completed_at": "2022-03-29T18:46:11.928122Z"}, {"name": "execute", "started_at": "2022-03-29T18:46:11.928376Z", "completed_at": "2022-03-29T18:46:11.928388Z"}], "thread_id": "Thread-1", "execution_time": 0.00897073745727539, "adapter_response": {}, "message": null, "failures": null, "unique_id": "test.smartpill.relationships_quickbook_purchases_lines_account_expense_account_id__id__ref_quickbook_accounts_.ba8e9f034e"}, {"status": "success", "timing": [{"name": "compile", "started_at": "2022-03-29T18:46:11.929593Z", "completed_at": "2022-03-29T18:46:11.935955Z"}, {"name": "execute", "started_at": "2022-03-29T18:46:11.936204Z", "completed_at": "2022-03-29T18:46:11.936216Z"}], "thread_id": "Thread-1", "execution_time": 0.007340192794799805, "adapter_response": {}, "message": null, "failures": null, "unique_id": "test.smartpill.relationships_quickbook_purchases_lines_account_expense_class_id__id__ref_quickbook_classes_.bc7751dae0"}, {"status": "success", "timing": [{"name": "compile", "started_at": "2022-03-29T18:46:11.937461Z", "completed_at": "2022-03-29T18:46:11.943544Z"}, {"name": "execute", "started_at": "2022-03-29T18:46:11.943793Z", "completed_at": "2022-03-29T18:46:11.943806Z"}], "thread_id": "Thread-1", "execution_time": 0.007031679153442383, "adapter_response": {}, "message": null, "failures": null, "unique_id": "test.smartpill.relationships_quickbook_purchases_lines_account_expense_customer_id__id__ref_quickbook_customers_.77011ad8ce"}, {"status": "success", "timing": [{"name": "compile", "started_at": "2022-03-29T18:46:11.945016Z", "completed_at": "2022-03-29T18:46:11.989165Z"}, {"name": "execute", "started_at": "2022-03-29T18:46:11.989480Z", "completed_at": "2022-03-29T18:46:11.989496Z"}], "thread_id": "Thread-1", "execution_time": 0.04527091979980469, "adapter_response": {}, "message": null, "failures": null, "unique_id": "model.smartpill.patients_status_historic"}, {"status": "success", "timing": [{"name": "compile", "started_at": "2022-03-29T18:46:11.991114Z", "completed_at": "2022-03-29T18:46:12.018749Z"}, {"name": "execute", "started_at": "2022-03-29T18:46:12.019052Z", "completed_at": "2022-03-29T18:46:12.019067Z"}], "thread_id": "Thread-1", "execution_time": 0.028996706008911133, "adapter_response": {}, "message": null, "failures": null, "unique_id": "model.smartpill.quickbook_general_ledger"}, {"status": "success", "timing": [{"name": "compile", "started_at": "2022-03-29T18:46:12.021582Z", "completed_at": "2022-03-29T18:46:12.101412Z"}, {"name": "execute", "started_at": "2022-03-29T18:46:12.101701Z", "completed_at": "2022-03-29T18:46:12.101714Z"}], "thread_id": "Thread-1", "execution_time": 0.08248758316040039, "adapter_response": {}, "message": null, "failures": null, "unique_id": "model.smartpill.goodpill_historic"}, {"status": "success", "timing": [{"name": "compile", "started_at": "2022-03-29T18:46:12.104232Z", "completed_at": "2022-03-29T18:46:12.142956Z"}, {"name": "execute", "started_at": "2022-03-29T18:46:12.143219Z", "completed_at": "2022-03-29T18:46:12.143233Z"}], "thread_id": "Thread-1", "execution_time": 0.040576934814453125, "adapter_response": {}, "message": null, "failures": null, "unique_id": "model.smartpill.patients_calendar"}, {"status": "success", "timing": [{"name": "compile", "started_at": "2022-03-29T18:46:12.302545Z", "completed_at": "2022-03-29T18:46:12.308536Z"}, {"name": "execute", "started_at": "2022-03-29T18:46:12.308806Z", "completed_at": "2022-03-29T18:46:12.308817Z"}], "thread_id": "Thread-1", "execution_time": 0.007289409637451172, "adapter_response": {}, "message": null, "failures": null, "unique_id": "model.smartpill.quickbook_general_ledger_abt"}, {"status": "success", "timing": [{"name": "compile", "started_at": "2022-03-29T18:46:12.309850Z", "completed_at": "2022-03-29T18:46:12.315829Z"}, {"name": "execute", "started_at": "2022-03-29T18:46:12.316083Z", "completed_at": "2022-03-29T18:46:12.316093Z"}], "thread_id": "Thread-1", "execution_time": 0.006873130798339844, "adapter_response": {}, "message": null, "failures": null, "unique_id": "model.smartpill.goodpill_historic_abt"}, {"status": "success", "timing": [{"name": "compile", "started_at": "2022-03-29T18:46:12.317184Z", "completed_at": "2022-03-29T18:46:12.352190Z"}, {"name": "execute", "started_at": "2022-03-29T18:46:12.352490Z", "completed_at": "2022-03-29T18:46:12.352503Z"}], "thread_id": "Thread-1", "execution_time": 0.03687453269958496, "adapter_response": {}, "message": null, "failures": null, "unique_id": "model.smartpill.patients_calendar_abt"}, {"status": "success", "timing": [{"name": "compile", "started_at": "2022-03-29T18:46:12.354606Z", "completed_at": "2022-03-29T18:46:12.373053Z"}, {"name": "execute", "started_at": "2022-03-29T18:46:12.373420Z", "completed_at": "2022-03-29T18:46:12.373434Z"}], "thread_id": "Thread-1", "execution_time": 0.01957392692565918, "adapter_response": {}, "message": null, "failures": null, "unique_id": "model.smartpill.goodpill_snapshot"}, {"status": "success", "timing": [{"name": "compile", "started_at": "2022-03-29T18:46:12.375148Z", "completed_at": "2022-03-29T18:46:12.380368Z"}, {"name": "execute", "started_at": "2022-03-29T18:46:12.380644Z", "completed_at": "2022-03-29T18:46:12.380656Z"}], "thread_id": "Thread-1", "execution_time": 0.006216287612915039, "adapter_response": {}, "message": null, "failures": null, "unique_id": "model.smartpill.goodpill_snapshot_abt"}], "elapsed_time": 3.3237550258636475, "args": {"write_json": true, "use_colors": true, "printer_width": 120, "version_check": true, "partial_parse": true, "static_parser": true, "profiles_dir": "/data", "send_anonymous_usage_stats": false, "event_buffer_size": 100000, "project_dir": "/data/git_repo", "compile": true, "which": "generate", "rpc_method": "docs.generate", "indirect_selection": "eager"}}